galago_tools-0.19.5.dist-info/licenses/LICENSE
tools/__init__.py
tools/app_config.py
tools/base_server.py
tools/cli.py
tools/command_args.py
tools/conda_utils.py
tools/discover_tools.py
tools/favicon.ico
tools/index.html
tools/launch_console.py
tools/launch_tools.py
tools/site_logo.png
tools/utils.py
tools/version.py
tools/web_server.py
tools/alps3000/__init__.py
tools/alps3000/driver.py
tools/alps3000/server.py
tools/bioshake/__init__.py
tools/bioshake/driver.py
tools/bioshake/server.py
tools/bravo/__init__.py
tools/bravo/driver.py
tools/bravo/server.py
tools/comms/__init__.py
tools/comms/tcpip.py
tools/cytation/__init__.py
tools/cytation/driver.py
tools/cytation/server.py
tools/dataman70/__init__.py
tools/dataman70/driver.py
tools/dataman70/server.py
tools/grpc_interfaces/alps3000_pb2.py
tools/grpc_interfaces/alps3000_pb2_grpc.py
tools/grpc_interfaces/bioshake_pb2.py
tools/grpc_interfaces/bioshake_pb2_grpc.py
tools/grpc_interfaces/bravo_pb2.py
tools/grpc_interfaces/bravo_pb2_grpc.py
tools/grpc_interfaces/controller_pb2.py
tools/grpc_interfaces/controller_pb2_grpc.py
tools/grpc_interfaces/cytation_pb2.py
tools/grpc_interfaces/cytation_pb2_grpc.py
tools/grpc_interfaces/dataman70_pb2.py
tools/grpc_interfaces/dataman70_pb2_grpc.py
tools/grpc_interfaces/hamilton_pb2.py
tools/grpc_interfaces/hamilton_pb2_grpc.py
tools/grpc_interfaces/hig_centrifuge_pb2.py
tools/grpc_interfaces/hig_centrifuge_pb2_grpc.py
tools/grpc_interfaces/labware_pb2.py
tools/grpc_interfaces/labware_pb2_grpc.py
tools/grpc_interfaces/liconic_pb2.py
tools/grpc_interfaces/liconic_pb2_grpc.py
tools/grpc_interfaces/microserve_pb2.py
tools/grpc_interfaces/microserve_pb2_grpc.py
tools/grpc_interfaces/multidrop_pb2.py
tools/grpc_interfaces/multidrop_pb2_grpc.py
tools/grpc_interfaces/opentrons2_pb2.py
tools/grpc_interfaces/opentrons2_pb2_grpc.py
tools/grpc_interfaces/pf400_pb2.py
tools/grpc_interfaces/pf400_pb2_grpc.py
tools/grpc_interfaces/plateloc_pb2.py
tools/grpc_interfaces/plateloc_pb2_grpc.py
tools/grpc_interfaces/plr_pb2.py
galago_tools-0.19.5.dist-info/METADATA
galago_tools-0.19.5.dist-info/WHEEL
galago_tools-0.19.5.dist-info/entry_points.txt
galago_tools-0.19.5.dist-info/top_level.txt
galago_tools-0.19.5.dist-info/RECORD
